llama_index/packs/agent_search_retriever/__init__.py
llama_index/packs/agent_search_retriever/base.py
llama_index_packs_agent_search_retriever-0.4.1.dist-info/METADATA
llama_index_packs_agent_search_retriever-0.4.1.dist-info/WHEEL
llama_index_packs_agent_search_retriever-0.4.1.dist-info/licenses/LICENSE
llama_index_packs_agent_search_retriever-0.4.1.dist-info/RECORD
