Metadata-Version: 2.4
Name: llama-index-packs-agent-search-retriever
Version: 0.4.1
Summary: llama-index packs agent_search_retriever integration
Author-email: Your Name <you@example.com>
Maintainer: logan-markewich
License-Expression: MIT
License-File: LICENSE
Keywords: agent,retriever,search
Requires-Python: <3.12,>=3.9
Requires-Dist: llama-index-core<0.15,>=0.13.0
